odoo/addons/mail_block_user_assigned_message/README.rst
odoo/addons/mail_block_user_assigned_message/__init__.py
odoo/addons/mail_block_user_assigned_message/__manifest__.py
odoo/addons/mail_block_user_assigned_message/models/__init__.py
odoo/addons/mail_block_user_assigned_message/models/mail_thread.py
odoo/addons/mail_block_user_assigned_message/models/res_partner.py
odoo/addons/mail_block_user_assigned_message/static/description/icon.png
odoo/addons/mail_block_user_assigned_message/views/res_users_views.xml
odoo_addon_mail_block_user_assigned_message-16.0.1.0.0.3.dist-info/METADATA
odoo_addon_mail_block_user_assigned_message-16.0.1.0.0.3.dist-info/WHEEL
odoo_addon_mail_block_user_assigned_message-16.0.1.0.0.3.dist-info/top_level.txt
odoo_addon_mail_block_user_assigned_message-16.0.1.0.0.3.dist-info/RECORD
