Metadata-Version: 2.1
Name: odoo-addon-mail_block_user_assigned_message
Version: 16.0.1.0.0.3
Requires-Python: >=3.10
Requires-Dist: odoo>=16.0a,<16.1dev
Summary: Block assignation notifications depending on model
Home-page: https://github.com/sygel-technology/sy-social
License: AGPL-3
Author: Sygel, Odoo Community Association (OCA)
Author-email: support@odoo-community.org
Classifier: Programming Language :: Python
Classifier: Framework :: Odoo
Classifier: Framework :: Odoo :: 16.0
Classifier: License :: OSI Approved :: GNU Affero General Public License v3
